reston/__init__.py
reston/core/__init__.py
reston/core/analysis.py
reston/core/anconf.py
reston/core/apk.py
reston/core/bytecode.py
reston/core/dvm.py
reston/core/zipfile.py
reston/decompiler/__init__.py
reston/decompiler/decompiler.py
reston/decompiler/dad/__init__.py
reston/decompiler/dad/ast.py
reston/decompiler/dad/basic_blocks.py
reston/decompiler/dad/control_flow.py
reston/decompiler/dad/dataflow.py
reston/decompiler/dad/decompile.py
reston/decompiler/dad/graph.py
reston/decompiler/dad/instruction.py
reston/decompiler/dad/node.py
reston/decompiler/dad/opcode_ins.py
reston/decompiler/dad/util.py
reston/decompiler/dad/writer.py
reston-0.4.dist-info/DESCRIPTION.rst
reston-0.4.dist-info/METADATA
reston-0.4.dist-info/RECORD
reston-0.4.dist-info/WHEEL
reston-0.4.dist-info/metadata.json
reston-0.4.dist-info/top_level.txt
