Metadata-Version: 2.0
Name: reston
Version: 0.4
Summary: Reston is a reverse engine framwork, current can play with Android files.
Home-page: http://github.com/zeaphoo/reston/
Author: zeaphoo
Author-email: zeaphoo@gmail.com
License: Apache
Platform: UNKNOWN
Requires-Dist: cryptography (>=1.0)
Requires-Dist: future
Requires-Dist: pyasn1
Requires-Dist: pygments
